{
  "0": "Books",
  "1": "Games and Toys",
  "2": "Furniture",
  "3": "Home Decor",
  "4": "Bedding",
  "5": "Beauty Products",
  "6": "Jewelry",
  "7": "Accessories",
  "8": "Garden and DIY",
  "9": "Sports Equipment",
  "10": "Clothing and Shoes",
  "11": "Leather Goods",
  "12": "Electronics - Phones",
  "13": "Electronics - Computers",
  "14": "Home Appliances",
  "15": "Video Games",
  "16": "Audio Video Equipment",
  "17": "Image and Sound",
  "18": "Office Supplies",
  "19": "Food and Beverages",
  "20": "Automotive",
  "21": "Pet Supplies",
  "22": "Baby Products",
  "23": "Wines and Spirits",
  "24": "Office Equipment",
  "25": "Musical Instruments",
  "26": "Perfumes and Cosmetics"
}
